pysolscan/__init__.py
pysolscan/solscan.py
pysolscan-0.0.6.dist-info/LICENSE
pysolscan-0.0.6.dist-info/METADATA
pysolscan-0.0.6.dist-info/WHEEL
pysolscan-0.0.6.dist-info/top_level.txt
pysolscan-0.0.6.dist-info/RECORD
