Metadata-Version: 2.1
Name: pysolscan
Version: 0.0.6
Summary: Minimal python wrapper for Solscan.io Api
Home-page: https://github.com/aryabhthakur/pysolscan
Author: Aryabh
Author-email: aryabharise@gmail.com
Project-URL: Bug Tracker, https://github.com/aryabhthakur/pysolscan/issues
Classifier: Programming Language :: Python :: 3
Classifier: License :: OSI Approved :: MIT License
Requires-Python: >=3.6
License-File: LICENSE
